yuck/__init__.py
yuck/yuck_function.py
pyuck-0.1.0.dist-info/LICENSE
pyuck-0.1.0.dist-info/METADATA
pyuck-0.1.0.dist-info/WHEEL
pyuck-0.1.0.dist-info/top_level.txt
pyuck-0.1.0.dist-info/RECORD
