Metadata-Version: 2.1
Name: pyuck
Version: 0.1.0
Summary: A Python package for creating functional singletons
Author-email: Xpo Development <dev@xpo.dev>
Project-URL: Homepage, https://github.com/xpodev/pyuck
Project-URL: Issues, https://github.com/xpodev/pyuck/issues
Classifier: Programming Language :: Python :: 3
Classifier: License :: OSI Approved :: MIT License
Classifier: Operating System :: OS Independent
Requires-Python: >=3.8
License-File: LICENSE
